<?xml version="1.0" encoding="UTF-8"?>
<XnaContent>?    
    <Dungeon ObjectName="invisible block" LocationX="40" LocationY="200" />?
    <Dungeon ObjectName="invisible block" LocationX="40" LocationY="240" />?
    <Dungeon ObjectName="invisible block" LocationX="40" LocationY="280" />?
    
    <Dungeon ObjectName="invisible block" LocationX="40" LocationY="400" />?
    <Dungeon ObjectName="invisible block" LocationX="40" LocationY="440" />?
    <Dungeon ObjectName="invisible block" LocationX="40" LocationY="480" />?
    
    <Dungeon ObjectName="invisible block" LocationX="560" LocationY="200" />?
    <Dungeon ObjectName="invisible block" LocationX="560" LocationY="240" />?
    <Dungeon ObjectName="invisible block" LocationX="560" LocationY="280" />?
    
    <Dungeon ObjectName="invisible block" LocationX="560" LocationY="400" />?
    <Dungeon ObjectName="invisible block" LocationX="560" LocationY="440" />?
    <Dungeon ObjectName="invisible block" LocationX="560" LocationY="480" />?
    
    <Dungeon ObjectName="invisible block" LocationX="80" LocationY="180" />?
    <Dungeon ObjectName="invisible block" LocationX="120" LocationY="180" />?
    <Dungeon ObjectName="invisible block" LocationX="160" LocationY="180" />?
    <Dungeon ObjectName="invisible block" LocationX="200" LocationY="180" />?
    <Dungeon ObjectName="invisible block" LocationX="240" LocationY="180" />?
  
    <Dungeon ObjectName="invisible block" LocationX="360" LocationY="180" />?
    <Dungeon ObjectName="invisible block" LocationX="400" LocationY="180" />?
    <Dungeon ObjectName="invisible block" LocationX="440" LocationY="180" />?
    <Dungeon ObjectName="invisible block" LocationX="480" LocationY="180" />?
    <Dungeon ObjectName="invisible block" LocationX="520" LocationY="180" />?
   
    <Dungeon ObjectName="invisible block" LocationX="80" LocationY="500" />?
    <Dungeon ObjectName="invisible block" LocationX="120" LocationY="500" />?
    <Dungeon ObjectName="invisible block" LocationX="160" LocationY="500" />?
    <Dungeon ObjectName="invisible block" LocationX="200" LocationY="500" />?
    <Dungeon ObjectName="invisible block" LocationX="240" LocationY="500" />?
  
    <Dungeon ObjectName="invisible block" LocationX="360" LocationY="500" />?
    <Dungeon ObjectName="invisible block" LocationX="400" LocationY="500" />?
    <Dungeon ObjectName="invisible block" LocationX="440" LocationY="500" />?
    <Dungeon ObjectName="invisible block" LocationX="480" LocationY="500" />?
    <Dungeon ObjectName="invisible block" LocationX="520" LocationY="500" />?
?</XnaContent>